pinax/__init__.py
pinax/announcements/__init__.py
pinax/announcements/admin.py
pinax/announcements/auth_backends.py
pinax/announcements/forms.py
pinax/announcements/models.py
pinax/announcements/signals.py
pinax/announcements/urls.py
pinax/announcements/views.py
pinax/announcements/migrations/0001_initial.py
pinax/announcements/migrations/__init__.py
pinax/announcements/templatetags/__init__.py
pinax/announcements/templatetags/pinax_announcements_tags.py
pinax/announcements/tests/__init__.py
pinax/announcements/tests/test.py
pinax/announcements/tests/tests.py
pinax/announcements/tests/urls.py
pinax_announcements-4.0.0.dist-info/AUTHORS
pinax_announcements-4.0.0.dist-info/LICENSE
pinax_announcements-4.0.0.dist-info/METADATA
pinax_announcements-4.0.0.dist-info/WHEEL
pinax_announcements-4.0.0.dist-info/top_level.txt
pinax_announcements-4.0.0.dist-info/RECORD
